drt_sdk/__init__.py
drt_sdk/abi/__init__.py
drt_sdk/abi/abi.py
drt_sdk/abi/abi_definition.py
drt_sdk/abi/abi_test.py
drt_sdk/abi/address_value.py
drt_sdk/abi/address_value_test.py
drt_sdk/abi/array_value.py
drt_sdk/abi/array_value_test.py
drt_sdk/abi/bigint_value.py
drt_sdk/abi/biguint_value.py
drt_sdk/abi/bool_value.py
drt_sdk/abi/bytes_value.py
drt_sdk/abi/bytes_value_test.py
drt_sdk/abi/codec.py
drt_sdk/abi/constants.py
drt_sdk/abi/counted_variadic_values.py
drt_sdk/abi/counted_variadic_values_test.py
drt_sdk/abi/enum_value.py
drt_sdk/abi/enum_value_test.py
drt_sdk/abi/fields.py
drt_sdk/abi/fields_test.py
drt_sdk/abi/interface.py
drt_sdk/abi/list_value.py
drt_sdk/abi/list_value_test.py
drt_sdk/abi/multi_value.py
drt_sdk/abi/multi_value_test.py
drt_sdk/abi/option_value.py
drt_sdk/abi/option_value_test.py
drt_sdk/abi/optional_value.py
drt_sdk/abi/optional_value_test.py
drt_sdk/abi/parts.py
drt_sdk/abi/serializer.py
drt_sdk/abi/serializer_test.py
drt_sdk/abi/shared.py
drt_sdk/abi/shared_test.py
drt_sdk/abi/small_int_values.py
drt_sdk/abi/string_value.py
drt_sdk/abi/string_value_test.py
drt_sdk/abi/struct_value.py
drt_sdk/abi/struct_value_test.py
drt_sdk/abi/token_identifier_value.py
drt_sdk/abi/tuple_value.py
drt_sdk/abi/tuple_value_test.py
drt_sdk/abi/type_formula.py
drt_sdk/abi/type_formula_parser.py
drt_sdk/abi/type_formula_parser_test.py
drt_sdk/abi/typesystem.py
drt_sdk/abi/typesystem_test.py
drt_sdk/abi/variadic_values.py
drt_sdk/abi/variadic_values_test.py
drt_sdk/adapters/__init__.py
drt_sdk/adapters/query_runner_adapter.py
drt_sdk/converters/__init__.py
drt_sdk/converters/errors.py
drt_sdk/converters/transactions_converter.py
drt_sdk/converters/transactions_converter_test.py
drt_sdk/core/__init__.py
drt_sdk/core/account.py
drt_sdk/core/account_test.py
drt_sdk/core/address.py
drt_sdk/core/address_test.py
drt_sdk/core/bech32.py
drt_sdk/core/code_metadata.py
drt_sdk/core/code_metadata_test.py
drt_sdk/core/codec.py
drt_sdk/core/codec_test.py
drt_sdk-0.0.1.dist-info/METADATA
drt_sdk-0.0.1.dist-info/WHEEL
drt_sdk-0.0.1.dist-info/licenses/LICENSE
drt_sdk-0.0.1.dist-info/RECORD
